symphonic/__init__.py
symphonic/core/__init__.py
symphonic/core/cli.py
symphonic/orchestrators/__init__.py
symphonic/providers/__init__.py
symphonic-0.1.0.dist-info/LICENSE
symphonic-0.1.0.dist-info/METADATA
symphonic-0.1.0.dist-info/WHEEL
symphonic-0.1.0.dist-info/RECORD
